libcythonconst/__init__.py
libcythonconst/lsum.c
libcythonconst/lsum.cpython-311-darwin.so
libcythonconst/lsum.h
libcythonconst/lsum.pxd
libcythonconst/lsum.pyx
libcythonconst-1.0.1.dist-info/METADATA
libcythonconst-1.0.1.dist-info/WHEEL
libcythonconst-1.0.1.dist-info/top_level.txt
libcythonconst-1.0.1.dist-info/RECORD
